bed_apy/__init__.py
bed_apy/bed_apy.py
bed_apy-0.2.5a0.dist-info/licenses/LICENSE
bed_apy-0.2.5a0.dist-info/METADATA
bed_apy-0.2.5a0.dist-info/WHEEL
bed_apy-0.2.5a0.dist-info/top_level.txt
bed_apy-0.2.5a0.dist-info/RECORD
