Metadata-Version: 2.4
Name: bed_apy
Version: 0.2.5a0
Summary: A Bedrock WebSocket system for Minecraft Python modding
Author: Ezekiel Nogle
Classifier: Programming Language :: Python :: 3
Classifier: License :: OSI Approved :: GNU General Public License v3 or later (GPLv3+)
Classifier: Operating System :: OS Independent
License-File: LICENSE
Requires-Dist: websockets
Requires-Dist: asyncio
Dynamic: license-file
